pspy-1.8.2.dist-info/RECORD
pspy-1.8.2.dist-info/LICENSE
pspy-1.8.2.dist-info/WHEEL
pspy-1.8.2.dist-info/entry_points.txt
pspy-1.8.2.dist-info/METADATA
pspy/pspy_utils.py
pspy/so_config.py
pspy/so_consistency.py
pspy/so_cov.py
pspy/so_window.py
pspy/so_misc.py
pspy/__init__.py
pspy/so_dict.py
pspy/sph_tools.py
pspy/_mcm_fortran.cpython-313-darwin.so
pspy/flat_tools.py
pspy/so_spectra.py
pspy/fft.py
pspy/so_map.py
pspy/so_mpi.py
pspy/_cov_fortran.cpython-313-darwin.so
pspy/so_map_preprocessing.py
pspy/so_mcm.py
pspy/tests/test_pspy_namaster.py
pspy/tests/test_so_map.py
pspy/tests/test_so_spectra.py
pspy/tests/test_so_dict.py
pspy/tests/test_so_cov.py
pspy/tests/data/generate_test_data.py
pspy/tests/data/test_data.pkl
pspy/tests/data/bode_almost_wmap5_lmax_1e4_lensedCls_startAt2.dat
pspy/tests/data/parameters_test_data.yml
pspy/.dylibs/libgfortran.5.dylib
pspy/.dylibs/libquadmath.0.dylib
pspy/.dylibs/libgcc_s.1.1.dylib
pspy/.dylibs/libgomp.1.dylib
pspy/scripts/test_pspy.py
