Metadata-Version: 2.1
Name: pspy
Version: 1.8.2
Summary: Python power spectrum code
Keywords: power spectra,cosmology
Author: Simons Observatory Collaboration Power Spectrum Task Force
Maintainer-Email: Thibaut Louis <thibaut.louis@ijclab.in2p3.fr>
License: 
Classifier: Development Status :: 5 - Production/Stable
Classifier: Operating System :: OS Independent
Classifier: Environment :: Console
Classifier: License :: OSI Approved :: BSD License
Classifier: Topic :: Scientific/Engineering :: Astronomy
Classifier: License :: OSI Approved :: GNU Lesser General Public License v3 (LGPLv3)
Classifier: Programming Language :: Python :: 3.9
Classifier: Programming Language :: Python :: 3.10
Classifier: Programming Language :: Python :: 3.11
Classifier: Programming Language :: Python :: 3.12
Classifier: Programming Language :: Python :: 3.13
Project-URL: Homepage, https://github.com/simonsobs/pspy
Project-URL: Documentation, https://pspy.readthedocs.io
Project-URL: Source, https://github.com/simonsobs/pspy
Project-URL: Tracker, https://github.com/simonsobs/pspy/issues
Project-URL: Licensing, https://github.com/simonsobs/pspy/blob/master/LICENCE
Requires-Python: >=3.9.0
Requires-Dist: pixell>=0.29.0
Provides-Extra: test
Requires-Dist: pytest; extra == "test"
Requires-Dist: pytest-cov; extra == "test"
Requires-Dist: camb; extra == "test"
Provides-Extra: notebook
Requires-Dist: jupyter; extra == "notebook"
Requires-Dist: ipykernel; extra == "notebook"
